imhotep_mail/__init__.py
imhotep_mail/cli.py
imhotep_mail/main.py
imhotep_mail-1.0.0.dist-info/licenses/LICENSE
imhotep_mail-1.0.0.dist-info/METADATA
imhotep_mail-1.0.0.dist-info/WHEEL
imhotep_mail-1.0.0.dist-info/entry_points.txt
imhotep_mail-1.0.0.dist-info/top_level.txt
imhotep_mail-1.0.0.dist-info/RECORD
