Metadata-Version: 2.4
Name: imhotep_mail
Version: 1.0.0
Summary: A python library to send mails easily
Home-page: https://github.com/Imhotep-Tech/imhotep_mail
Author: Karim Bassem
Author-email: imhoteptech@outlook.com
License: MIT
Keywords: email,smtp,flask-mail,imhotep
Classifier: Programming Language :: Python :: 3
Classifier: License :: OSI Approved :: MIT License
Classifier: Operating System :: OS Independent
Requires-Python: >=3.6
License-File: LICENSE
Requires-Dist: Flask
Requires-Dist: flask_mail
Requires-Dist: dotenv
Dynamic: author
Dynamic: author-email
Dynamic: classifier
Dynamic: description
Dynamic: description-content-type
Dynamic: home-page
Dynamic: keywords
Dynamic: license
Dynamic: license-file
Dynamic: requires-dist
Dynamic: requires-python
Dynamic: summary
